Metadata-Version: 1.0
Name: speed-predict
Version: 0.0
Summary: forecasting package
Home-page: UNKNOWN
Author: UNKNOWN
Author-email: jacoblouiswright@gmail.com
License: UNKNOWN
Platform: UNKNOWN
